metricsFacade/__init__.py
metricsFacade/abstractMetricProducer.py
metricsFacade/advertCrawlTimeSecondsMetric.py
metricsFacade/errorCategory.py
metricsFacade/errorCounterMetric.py
metricsFacade/filledFieldsMetric.py
metricsFacade/labelsList.py
metricsFacade/metricType.py
metricsFacade/metricsProducer.py
metricsFacade/moduleName.py
metricsFacade/kafkaMetricsSchema/__init__.py
metricsFacade/kafkaMetricsSchema/schema_classes.py
metricsFacade/kafkaMetricsSchema/com/__init__.py
metricsFacade/kafkaMetricsSchema/com/topkrabbensteam/__init__.py
metricsFacade/kafkaMetricsSchema/com/topkrabbensteam/zm/__init__.py
metricsFacade/kafkaMetricsSchema/com/topkrabbensteam/zm/custom_metric/__init__.py
metricsFacade/kafkaMetricsSchema/com/topkrabbensteam/zm/custom_metric/enums/__init__.py
metricsFacade/kafkaMetricsSchema/com/topkrabbensteam/zm/metrics/__init__.py
metricsFacade/kafkaMetricsSchema/com/topkrabbensteam/zm/metrics/metric_header/__init__.py
metricsFacade/kafkaMetricsSchema/com/topkrabbensteam/zm/metrics/prometheus_metric/__init__.py
kafka_metrics_producer_topkrabbensteam-1.0.dist-info/LICENSE
kafka_metrics_producer_topkrabbensteam-1.0.dist-info/METADATA
kafka_metrics_producer_topkrabbensteam-1.0.dist-info/WHEEL
kafka_metrics_producer_topkrabbensteam-1.0.dist-info/top_level.txt
kafka_metrics_producer_topkrabbensteam-1.0.dist-info/RECORD
