Metadata-Version: 2.1
Name: kafka-metrics-producer-topkrabbensteam
Version: 1.0
Summary: Library that can be used to produce metrics to Kafka using Apache Avro schemas
Home-page: https://github.com/YendiyarovSV/kafka-metrics-producer-topkrabbensteam
Author: Sergei Yendiyarov
Author-email: s.endiyarov@gmail.com
License: License :: OSI Approved :: Apache Software License
Requires-Dist: six (==1.11.0)
Requires-Dist: avro-gen-topkrabbensteam (>=0.0.2)
Requires-Dist: kafka-avro-producer-topkrabbensteam (>=1.2)
